{
    "url_original": "https://www.wsj.com/articles/china-bought-italian-military-drone-maker-without-authorities-knowledge-11636972513",
    "url": "china-bought-italian-military-drone-maker-without-authorities-knowledge-11636972513",
    "title": "China Bought Italian Military-Drone Maker Without Authorities’ Knowledge",
    "sub_head": "Sale illustrates Europe’s weak rules on purchases of sensitive technology",
    "category_1": "World",
    "image_1_url": "https://images.wsj.net/im-434130?width=860&height=573",
    "image_1": "im-434130.jpg",
    "time": "2021-11-15 05:35:00",
    "body": "In 2018, a Chinese state-controlled company bought an Italian manufacturer of military drones. Soon after, it began transferring the company’s know-how and technology—which had been used by the Italian military in Afghanistan—to China.<br />The Italian and European authorities had no knowledge of the move, revealing how Beijing is skirting weak investment-screening in Europe to acquire sensitive technology."
}