{
    "url_original": "https://www.wsj.com/articles/nissan-to-spend-17-6-billion-on-battery-powered-vehicles-over-five-years-11638147685?mod=business_lead_pos3",
    "url": "nissan-to-spend-17-6-billion-on-battery-powered-vehicles-over-five-years-11638147685",
    "title": "Nissan to Spend $17.6 Billion on Battery-Powered Vehicles Over Five Years",
    "sub_head": "Car maker says that by 2030 half of its vehicles sold will be powered at least partly by batteries",
    "category_1": "Business",
    "category_2": "Autos & Transportation",
    "time": "2021-11-28 23:46:00",
    "body": "TOKYO— Nissan  Motor Co. said Monday it plans to spend $17.6 billion over the next five years as it adds 20 new battery-powered vehicles to its lineup.<br />The company hopes to recapture a degree of the prominence it held in the electric-vehicle race after its pioneering introduction of the Leaf EV more than a decade ago. Investors have boosted the share prices of car makers that are betting big on EVs, including relative newcomers such as  Tesla Inc.  and industry stalwarts like  Ford Motor Co.  and  Volkswagen AG ."
}