{
    "url_original": "https://www.wsj.com/articles/stock-market-is-top-heavy-but-carnage-is-widespread-11652935180?mod=markets_lead_pos1",
    "url": "stock-market-is-top-heavy-but-carnage-is-widespread-11652935180",
    "title": "Stock Market Is Top-Heavy, but Carnage Is Widespread",
    "sub_head": "As former highfliers including Microsoft, Apple and Amazon falter, broader market feels pain",
    "category_1": "Markets",
    "time": "2022-05-19 05:30:00",
    "body": "Eight companies are to blame for nearly half the stock market’s decline this year—and the pain doesn’t end there.<br />Apple Inc.,   Microsoft Corp. ,  Amazon . com Inc.,  Tesla Inc .  and the parent companies of Google and  Facebook  swelled to be so big in recent years that they accounted for 25% of the S&P 500 heading into 2022. The benchmark U.S. stock index is weighted by market value, which means the biggest companies have the most influence."
}