{
    "url_original": "https://www.wsj.com/articles/activision-deal-is-set-to-power-microsofts-push-to-be-the-netflix-of-gaming-11642597205?mod=business_lead_pos1",
    "url": "activision-deal-is-set-to-power-microsofts-push-to-be-the-netflix-of-gaming-11642597205",
    "title": "Microsoft’s Activision Deal to Power Its Netflix-of-Gaming Aspirations",
    "sub_head": "The $75 billion acquisition would give the software company a new pool of games and gamers to entice to its cloud",
    "category_1": "Tech",
    "category_2": "Consumer Technology",
    "time": "2022-01-19 08:00:00",
    "body": "Microsoft Corp.’s  acquisition of  Activision Blizzard Inc.  is aimed at shaking up the game industry by building out the software giant’s library of blockbuster videogames and bolstering its efforts to entice consumers onto its cloud-gaming service.<br />The planned $75 billion deal would be Microsoft’s biggest ever and its most ambitious investment yet in its plan to turn its Game Pass subscription service into the  Netflix  of gaming. Once the acquisition closes, Microsoft said it will be the world’s third-largest game company by sales, with 30 game studios under its belt, including the developers of popular franchises Call of Duty, World of Warcraft and Candy Crush."
}