{
    "url_original": "https://www.wsj.com/articles/competition-for-compliance-officers-intensifies-amid-regulatory-pressures-11642623091?mod=business_minor_pos16",
    "url": "competition-for-compliance-officers-intensifies-amid-regulatory-pressures-11642623091",
    "title": "Competition for Compliance Officers Intensifies Amid Regulatory Pressures",
    "sub_head": "In a tight labor market, businesses are luring compliance staff with salary increases, remote-working opportunities and company equity",
    "category_1": "Risk & Compliance Journal",
    "image_1_url": "https://images.wsj.net/im-470240?width=860&height=573",
    "image_1": "im-470240.jpg",
    "time": "2022-01-19 15:11:00"
}