{
    "url_original": "https://www.wsj.com/articles/turo-files-for-ipo-11641861832?mod=markets_lead_pos10",
    "url": "turo-files-for-ipo-11641861832",
    "title": "Turo Files for IPO",
    "sub_head": "Car-sharing marketplace to set aside shares for its car owners and renters",
    "category_1": "Markets",
    "category_2": "Stocks",
    "image_1_url": "https://images.wsj.net/im-465333?width=860&height=573",
    "image_1": "im-465333.jpg",
    "time": "2022-01-10 19:43:00",
    "body": "Car-sharing marketplace Turo Inc. has publicly filed for its initial public offering and said that some of the car owners and renters could get a chance to participate in the offering.<br />Turo, whose marketplace allows private car owners to rent their cars, plans to allocate up to 5% of shares to be sold to some individuals, including hosts and guests who meet certain conditions, under what’s known as a directed-share program."
}