{
    "url_original": "https://www.wsj.com/articles/california-bill-aims-to-make-tech-firms-liable-for-social-media-addiction-in-children-11647382786?mod=tech_featst_pos1",
    "url": "california-bill-aims-to-make-tech-firms-liable-for-social-media-addiction-in-children-11647382786",
    "title": "California Bill Aims to Make Tech Firms Liable for Social-Media Addiction in Children",
    "sub_head": "The new bill adds to a stack of proposed legislature drawn up to curb social media’s influence over young people",
    "category_1": "CMO Today",
    "image_1_url": "https://images.wsj.net/im-505619?width=860&height=573",
    "image_1": "im-505619.jpg",
    "time": "2022-03-15 18:19:00",
    "body": "A pair of California lawmakers introduced a bill that aims to hold technology companies liable for social-media addictions that may affect children.<br />The bill would let parents and guardians sue platforms that they believe addicted children in their care through advertising, push notifications and design features that promote compulsive use, particularly the continual consumption of harmful content on issues such as eating disorders and suicide."
}