{
    "url_original": "https://www.wsj.com/articles/the-russia-ukraine-cyberwar-could-outlast-the-shooting-war-11646456442?mod=business_minor_pos7",
    "url": "the-russia-ukraine-cyberwar-could-outlast-the-shooting-war-11646456442",
    "title": "The Russia-Ukraine Cyberwar Could Outlast the Shooting War",
    "sub_head": "Cyberattacks by both sides could lead to the kind of collateral damage that is difficult to avoid in cyberspace",
    "category_1": "Tech",
    "category_2": "Keywords: Christopher Mims",
    "image_1_url": "https://images.wsj.net/im-498490?width=860&height=573",
    "image_1": "im-498490.jpg",
    "time": "2022-03-05 12:00:00",
    "body": "Alongside the physical violence of the Russian assault on Ukraine, a parallel cyberwar is under way that has little, if any, precedent.<br />The digital battle so far has proceeded in ways cyberwar specialists didn’t expect—and that has many of them concerned about how the technological dimensions of Europe’s worst conflict in decades will play out. In particular, they’re concerned about its potential to spill beyond the borders of the two combatants."
}