{
    "url_original": "https://www.wsj.com/articles/democrats-are-killing-the-american-dream-11620251334?mod=opinion_major_pos7",
    "url": "democrats-are-killing-the-american-dream-11620251334",
    "title": "Democrats Are Killing the American Dream",
    "sub_head": "Joe Biden’s American Families Plan replaces individual striving with middle class entitlements.",
    "category_1": "Opinion",
    "category_2": "Wonder Land",
    "image_1_url": "https://images.wsj.net/im-334480?width=620&size=1.5",
    "image_1": "im-334480.jpg",
    "time": "2021-05-05 17:48:00"
}