{
    "url_original": "https://www.wsj.com/articles/how-to-handle-your-re-entry-anxiety-as-the-pandemic-recedes-11621094399",
    "url": "how-to-handle-your-re-entry-anxiety-as-the-pandemic-recedes-11621094399",
    "title": "How to Handle Your Re-Entry Anxiety as the Pandemic Recedes",
    "sub_head": "Nervous about going out into the world again? Here are tips from a neuroscientist, a therapist, a behavioral scientist and a psychologist",
    "category_1": "Life & Arts",
    "category_2": "Bonds",
    "image_1_url": "https://images.wsj.net/im-338970?width=620&size=1.5",
    "image_1": "im-338970.jpg",
    "time": "2021-05-15 12:00:00"
}