{
    "url_original": "https://www.wsj.com/articles/the-american-institutions-we-love-11657046905?mod=opinion_lead_pos11",
    "url": "the-american-institutions-we-love-11657046905",
    "title": "The American Institutions We Love",
    "sub_head": "A Gallup report suggests that people aren’t big on politics or politicized organizations.",
    "category_1": "Opinion",
    "category_2": "Best of the Web",
    "image_1_url": "https://images.wsj.net/im-577297?width=860&height=573",
    "image_1": "im-577297.jpg",
    "time": "2022-07-05 14:48:00",
    "body": "Maybe businesses should just focus on profitably serving their customers. We live in an age when large corporations spend enormous amounts of time and resources acting on the advice of non-shareholding “stakeholders” and telling us how virtuous they are in following the latest political fads. They also ask Americans to believe that it’s right and just to focus intensely on racial differences among employees and prospective employees. And yet somehow the public doesn’t think large corporations are virtuous. But it isn’t because Americans don’t like business. The latest Gallup survey finds a notable exception to a general lack of faith in American institutions.<br />Jeffrey Jones of Gallup reports on the polling firm’s latest findings:"
}