{
    "url_original": "https://www.wsj.com/articles/us-economy-march-2022-retail-sales-11649877082",
    "url": "us-economy-march-2022-retail-sales-11649877082",
    "title": "Retail Spending Advanced in March as Inflation Surged, Economists Estimate",
    "sub_head": "Consumers are spending more on essentials like gasoline and food, cutting back on optional big-ticket purchases",
    "category_1": "Economy",
    "category_2": "Economic Data",
    "time": "2022-04-14 05:30:00",
    "body": "American shoppers kept opening their wallets in March as rapidly rising prices for gasoline, food and goods took up more of their spending, economists say.<br />Consumers are estimated to have increased their retail and restaurant spending by 0.6% in March compared with the previous month, according to economists surveyed by The Wall Street Journal. That would be a slight bump up from the modest monthly increase of 0.3% in February, according to the Commerce Department. The department will release its March retail-sales figures on Thursday at 8:30 a.m. ET."
}