{
    "url_original": "https://www.wsj.com/articles/sec-whistleblower-program-shows-value-of-speaking-up-departing-chief-says-11618607640?mod=business_minor_pos16",
    "url": "sec-whistleblower-program-shows-value-of-speaking-up-departing-chief-says-11618607640",
    "title": "SEC Whistleblower Program Shows Value of Speaking Up, Departing Chief Says",
    "sub_head": "Jane Norberg, who has served as chief of the whistleblower office since 2016, is leaving the agency on Friday",
    "category_1": "Risk & Compliance Journal",
    "image_1_url": "https://images.wsj.net/im-326420?width=620&size=1",
    "image_1": "im-326420.jpg",
    "time": "2021-04-16 17:14:00"
}