{
    "url_original": "https://www.wsj.com/articles/abandon-stocks-for-bonds-if-only-life-were-so-simple-11654939540?mod=markets_major_pos7",
    "url": "abandon-stocks-for-bonds-if-only-life-were-so-simple-11654939540",
    "title": "Abandon Stocks for Bonds? If Only Life Were So Simple.",
    "sub_head": "Investors who shunned bonds for years need to reassess their objections, even if there is no magic fix to the difficulties of inflation",
    "category_1": "Markets",
    "category_2": "Streetwise",
    "time": "2022-06-11 08:03:00",
    "body": "The good news: At last, there is a worthwhile alternative to stocks. Bonds sport far more attractive yields than they have in years.<br />The bad news: Benchmark U.S. Treasurys have been crushed this year alongside stocks. Both the 10-year bond and the S&P 500 were down an unlucky 13% for the year up to the middle of this week, although stocks were then hit much harder by Friday’s bad inflation figures than bonds were. Meanwhile junk bonds, the highest-yielding corporate bonds, bring similar exposure to a potential worsening of corporate fundamentals as shares."
}