{
    "url_original": "https://www.wsj.com/articles/cotton-prices-surge-to-highest-level-in-a-decade-11633426200?mod=business_lead_pos3",
    "url": "cotton-prices-surge-to-highest-level-in-a-decade-11633426200",
    "title": "Cotton Prices Surge to Highest Level in a Decade",
    "sub_head": "China buys up U.S. supplies of crop, even as Trump-era import ban limits use of Chinese-grown fiber",
    "category_1": "Markets",
    "category_2": "Commodities",
    "image_1_url": "https://images.wsj.net/im-410119?width=860&height=573",
    "image_1": "im-410119.jpg",
    "time": "2021-10-05 05:30:00",
    "body": "Cotton futures are trading at their highest price in about a decade, with growing Chinese demand being met in part by rising U.S. exports to China, a curiosity of Trump-era trade-war policies.<br />Most-active U.S. cotton futures trading on the  Intercontinental Exchange  closed Monday up 0.4% at $1.05 a pound, keeping prices at their highest level since September 2011. Prices have risen 18% higher over the past 10 sessions. Higher clothing prices could eventually follow."
}